{"cameraMode":{"drawMode":0,"name":"Shaded","section":"Shading Mode"},"sceneLighting":true,"audioPlay":false,"sceneViewState":{"m_AlwaysRefresh":false,"showFog":true,"showSkybox":true,"showFlares":true,"showImageEffects":true,"showParticleSystems":true,"showVisualEffectGraphs":true,"m_FxEnabled":true},"in2DMode":false,"pivot":{"x":-0.8902850151062012,"y":1.8524268865585328,"z":7.752283096313477},"rotation":{"x":0.0026949988678097727,"y":-0.9964954257011414,"z":-0.07607073336839676,"w":-0.035283446311950687},"size":0.7925578355789185,"orthographic":false}